IMG2GIF_package/__init__.py
IMG2GIF_package/converter.py
img2gif_package-1.0.0.dist-info/LICENSE
img2gif_package-1.0.0.dist-info/METADATA
img2gif_package-1.0.0.dist-info/WHEEL
img2gif_package-1.0.0.dist-info/top_level.txt
img2gif_package-1.0.0.dist-info/RECORD
